{"hash": "fd2f746242ead0eb", "card": {"id": "2026-07-12-mercado", "type": "blog", "title": "Mercados esta semana: energía solar, micro caps y el ruido de Reddit", "date": "2026-07-12", "summary": "Un repaso a lo que reportan los mercados esta semana: desde el interés renovado en acciones solares hasta la especulación en micro caps y el debate sobre BlackBerry en foros de inversión.", "cover": "public/media/blog/2026-07-12-mercado.png", "accent": "#4feeeb", "accent2": "#3c8ce2", "body": "## Lo que mueven los mercados esta semana\n\nBenzinga publicó esta semana dos listas que concentraron atención entre inversores minoristas: las mejores acciones del sector solar y las mejores acciones por debajo de cinco dólares. Ambas categorías tienen en común que atraen a quienes buscan exposición a temas de crecimiento o a precios de entrada bajos, aunque con perfiles de riesgo muy distintos.\n\nEso no es todo. En foros como Reddit's r/wallstreetbets, el tono de la semana mezcló anécdotas personales con especulación técnica sobre niveles de precio y apuestas de largo plazo en nombres como BlackBerry. Ninguno de esos comentarios constituye análisis formal, pero sí reflejan el estado de ánimo de una parte del mercado minorista.\n\n---\n\n## Energía solar: el sector que sigue en el radar\n\nBenzinga incluyó al sector solar entre sus temas destacados de la semana. El interés no es nuevo: las acciones de energías renovables han alternado períodos de euforia y corrección en los últimos tres años, impulsadas por política pública, tasas de interés y competencia con paneles de fabricación asiática.\n\nLo que reporta el mercado ahora es atención sostenida, no un pico de especulación. Algunos factores que los analistas suelen considerar al revisar este sector:\n\n- Subsidios federales en Estados Unidos bajo la Ley de Reducción de la Inflación (IRA), vigente desde 2022.\n- Márgenes comprimidos por el precio de los paneles solares chinos.\n- Demanda creciente de energía para centros de datos e infraestructura de inteligencia artificial.\n- Tasas de interés: las empresas solares suelen financiarse con deuda, por lo que tasas altas pesan sobre sus valuaciones.\n\nEl sector no es homogéneo. Hay diferencia entre fabricantes de paneles, desarrolladores de proyectos y empresas de servicios de instalación. Cada uno responde distinto a los mismos datos macroeconómicos.\n\n---\n\n## Acciones bajo cinco dólares: qué dice el interés en micro caps\n\nLa segunda lista de Benzinga cubre acciones de bajo precio unitario, lo que el mercado anglosajón llama penny stocks o micro caps. El sentimiento registrado fue positivo moderado.\n\nEs útil separar dos cosas aquí:\n\n**El precio por acción no equivale a valuación barata.** Una acción a cuatro dólares puede tener una capitalización de mercado enorme si hay miles de millones de acciones en circulación. Y al revés: una acción a 800 dólares puede ser barata si sus utilidades lo justifican.\n\nLo que sí describe el interés en este segmento es apetito por riesgo. Cuando los inversores minoristas buscan nombres de bajo precio, suelen hacerlo buscando porcentajes de ganancia altos en poco tiempo. Ese comportamiento históricamente se intensifica en momentos de optimismo general en el mercado.\n\n---\n\n## Reddit y el ruido de corto plazo\n\nEsta semana, r/wallstreetbets registró publicaciones sobre tres temas: el cierre de una posición sin contexto claro, una anécdota personal sobre ganancias, y una tesis de largo plazo sobre BlackBerry basada en su división de software QNX.\n\nEl caso de BlackBerry es el único con contenido analítico. QNX es el sistema operativo que BlackBerry vende para vehículos y dispositivos industriales. La tesis que circula en el foro sostiene que la adopción de vehículos conectados podría aumentar la demanda de ese software. No es una idea nueva, y la empresa lleva años intentando convertir esa división en su motor de crecimiento.\n\nEl sentimiento registrado en todas las publicaciones de Reddit fue neutral. Eso es coherente con lo que se observa: no hay un tema dominante ni una narrativa clara que esté moviendo al foro esta semana.\n\nTambién circuló especulación técnica sobre niveles de soporte y resistencia en un activo no identificado, con referencias a posibles compresiones de posiciones cortas (squeezes). Sin identificar el activo ni la fuente de los datos, ese tipo de publicación no ofrece información accionable para nadie fuera del hilo.\n\n---\n\n## Preguntas frecuentes\n\n**¿Por qué importa lo que dice Reddit sobre los mercados?**\nNo importa como fuente de análisis, pero sí como termómetro del sentimiento minorista. Cuando un tema concentra muchas publicaciones positivas en foros de inversión, eso puede traducirse en flujo de órdenes hacia esos activos. El caso GameStop en 2021 es el ejemplo más conocido. Esta semana el tono es más disperso y sin un tema dominante.\n\n**¿Las listas de mejores acciones de Benzinga son recomendaciones de inversión?**\nNo. Son contenido editorial que agrupa nombres según criterios definidos por el medio, como precio, sector o capitalización. Sirven para identificar qué temas están en la conversación del mercado, no para decidir qué hacer con el dinero.\n\n**¿Qué es QNX y por qué importa para BlackBerry?**\nQNX es un sistema operativo de tiempo real que BlackBerry adquirió en 2010. Se usa principalmente en automóviles, equipos médicos y sistemas industriales. Representa la apuesta de la empresa por alejarse del negocio de teléfonos, en el que dejó de competir. Su adopción en vehículos conectados es real, aunque los ingresos que genera aún no han convencido al mercado de que justifican una valuación alta.\n\n---\n\n## En resumen\n\nLo que reporta el mercado esta semana no es un movimiento claro en una dirección. El interés en energía solar refleja un sector que sigue en la conversación, impulsado por política pública y demanda de infraestructura. El apetito por micro caps sugiere que el optimismo minorista no ha desaparecido. Y el ruido en Reddit es eso: ruido disperso sin narrativa dominante. La semana no ofrece una historia limpia, lo cual también es información.\n\n---\n\n*Mal Mercado es contenido educativo e informativo de análisis general de mercados: la misma información para todos los lectores. No es asesoría de inversión personalizada ni recomendación individualizada; no somos asesores registrados ante la CNBV. Invertir implica riesgo de pérdida. Los rendimientos pasados no garantizan rendimientos futuros. Cada quien es responsable de sus propias decisiones.*", "images": ["public/media/blog/2026-07-12-mercado-hero.png", "public/media/blog/2026-07-12-mercado-foto1.jpg", "public/media/blog/2026-07-12-mercado-foto2.jpg"], "image_credits": ["Alexsegrelles · BY-SA · vía wikimedia"], "sources": ["https://www.reddit.com/r/wallstreetbets/comments/1utyf4l/uh_oh_boys_strait_closed_again/", "https://www.reddit.com/r/wallstreetbets/comments/1uu0q0c/gf_broke_up_with_me_least_i_have_gains/", "https://www.reddit.com/r/wallstreetbets/comments/1uu2zpt/delulu_part_2_712_key_notes_squeeze_passed_or/", "https://www.reddit.com/r/wallstreetbets/comments/1utt8p5/longterm_bet_on_blackberry_due_to_qnx/", "https://www.benzinga.com/money/best-solar-stocks", "https://www.benzinga.com/money/top-stocks-under-5"], "read_min": 5, "category": "Acciones", "tags": ["acciones solares", "micro caps", "blackberry qnx", "mercado minorista", "reddit wallstreetbets", "energías renovables"], "social": {"youtube": "Título: Energía solar, micro caps y el ruido de Reddit: qué observa el mercado esta semana\nDescripción: Esta semana los mercados registraron atención renovada en acciones del sector solar, interés en micro caps por debajo de cinco dólares y debate en Reddit sobre BlackBerry y su división de software QNX. Mal Mercado analiza qué hay detrás de cada señal y qué factores reales podrían explicar el movimiento. Análisis completo en el blog: https://codemalo.github.io/Mal-Mercado/blog.html", "instagram": "Esta semana el mercado minorista miró hacia tres lugares al mismo tiempo: acciones solares con atención sostenida, micro caps de bajo precio con apetito de riesgo visible, y foros de Reddit donde circuló una tesis sobre BlackBerry y su software para vehículos conectados.\n\nNinguno de esos tres frentes opera en el mismo registro. El sector solar tiene fundamentos macroeconómicos concretos detrás, desde los subsidios de la IRA hasta la demanda de energía para centros de datos. Las micro caps responden más al estado de ánimo general que a datos específicos. Y Reddit mezcla anécdota con análisis en proporciones que conviene separar antes de sacar conclusiones.\n\nEl análisis completo está en el blog de Mal Mercado.\n#MalMercado #MercadosLatam #AccionesSolares #MicroCaps #InversionesInteligentes #AnalisisFinanciero #BlackBerry", "facebook": "Esta semana Mal Mercado observó tres temas que concentraron la atención del mercado minorista: el sector de energía solar, las acciones por debajo de cinco dólares y el debate en Reddit sobre BlackBerry.\n\nEl interés en acciones solares no responde esta vez a un pico especulativo, sino a atención sostenida apoyada en factores concretos: subsidios federales en Estados Unidos bajo la Ley de Reducción de la Inflación, demanda creciente de energía para infraestructura de inteligencia artificial y el impacto que las tasas de interés siguen teniendo sobre las valuaciones del sector. Las micro caps, por su parte, reflejan algo más simple: apetito por riesgo en un momento de optimismo moderado.\n\nEl caso BlackBerry es el más interesante del lote. Su división QNX para vehículos conectados lleva años siendo señalada como el motor de crecimiento que la empresa necesita. Que el tema vuelva a circular en foros de inversión dice algo sobre el estado de ánimo del mercado, aunque no necesariamente sobre los fundamentos. El análisis completo está disponible en el blog: https://codemalo.github.io/Mal-Mercado/blog.html", "tiktok": "El mercado minorista tuvo tres focos esta semana: acciones solares con atención real detrás, micro caps que reflejan apetito de riesgo, y Reddit debatiendo si BlackBerry y su software para autos conectados tiene algo concreto. Mal Mercado separa el ruido del análisis.\n#MalMercado #MercadosFinancieros #AccionesSolares #InversionLatam #BlackBerry", "x": "Energía solar con fundamentos reales, micro caps que reflejan apetito de riesgo y Reddit debatiendo BlackBerry otra vez. Mal Mercado analiza qué hay detrás de cada señal esta semana. https://codemalo.github.io/Mal-Mercado/blog.html", "threads": "Esta semana el mercado minorista miró al sector solar, a las acciones de bajo precio y a BlackBerry desde Reddit. Tres perfiles de riesgo muy distintos que el análisis conviene no mezclar. El desglose completo está en el blog de Mal Mercado.", "linkedin": "Los mercados esta semana ofrecieron tres señales que vale la pena leer por separado. El sector de energía solar registró atención sostenida, no especulativa, impulsada por factores estructurales como los subsidios de la Ley de Reducción de la Inflación en Estados Unidos, la demanda de energía para centros de datos vinculados a inteligencia artificial y el efecto persistente de las tasas de interés sobre las valuaciones de empresas intensivas en deuda. El segmento no es homogéneo: fabricantes de paneles, desarrolladores de proyectos y empresas de instalación responden de forma distinta a los mismos datos macro.\n\nEl interés en micro caps y acciones por debajo de cinco dólares cuenta una historia diferente. No se trata de valuaciones atractivas por precio unitario, sino de apetito por riesgo en un contexto de optimismo moderado. Históricamente, ese comportamiento se intensifica cuando el sentimiento general del mercado minorista se vuelve más constructivo.\n\nEn paralelo, foros como Reddit's r/wallstreetbets retomaron la tesis sobre BlackBerry y su división de software QNX para vehículos conectados. La idea lleva años circulando y tiene lógica sectorial, pero el sentimiento registrado fue neutral, sin narrativa dominante. Mal Mercado analiza estas señales con contexto y sin ruido. Análisis completo en el blog: https://codemalo.github.io/Mal-Mercado/blog.html"}}}