{"hash": "014cffff922f8d4a", "card": {"id": "2026-07-06-mercado", "type": "blog", "title": "Mercados en pausa: qué observa el mercado en la primera semana de julio 2026", "date": "2026-07-06", "summary": "El mercado entra a la semana del 6 de julio con pocas noticias concretas pero con preguntas abiertas sobre el precio del petróleo y el sentimiento general de los inversionistas.", "cover": "public/media/blog/2026-07-06-mercado.png", "accent": "#4feea3", "accent2": "#3cd7e2", "body": "La primera semana completa de julio 2026 arrancó sin grandes detonadores de noticias. Los foros de discusión más activos de Wall Street registraron conversaciones sobre petróleo, posicionamiento individual y una sensación generalizada de espera. Eso, de por sí, es un dato.\n\nCuando el ruido baja y los mercados no tienen un catalizador claro, el posicionamiento se vuelve más relevante que los titulares. Aquí está lo que se observó.\n\n## El petróleo, en el centro de la conversación\n\nUno de los temas que más circuló entre operadores minoristas durante el 6 de julio fue el comportamiento del precio del petróleo. La pregunta que se repetía: ¿qué está pasando con los precios?\n\nEsa pregunta abierta no es trivial. Cuando los participantes del mercado no tienen una narrativa clara para explicar un movimiento, suele ser porque las variables en juego son múltiples o contradictorias.\n\nAlgunos factores que el mercado ha estado procesando en torno al petróleo:\n\n- Decisiones de producción de la OPEP+ y sus miembros disidentes\n- Nivel de demanda global ante un crecimiento económico desigual\n- Inventarios semanales publicados por la EIA en Estados Unidos\n- La fortaleza o debilidad del dólar, que afecta directamente el precio del crudo denominado en esa moneda\n\nNinguno de estos factores opera de forma aislada. Un dólar fuerte puede presionar el precio hacia abajo aunque la demanda suba. La incertidumbre sobre ese balance explica por qué la pregunta circuló sin una respuesta definitiva.\n\n## Sentimiento neutral: qué significa en la práctica\n\nLos hilos de discusión del 6 de julio mostraron un sentimiento medido en cero, es decir, ni alcista ni bajista de forma predominante. Esto ocurre con más frecuencia de lo que se piensa, especialmente en semanas sin publicaciones de datos económicos mayores o resultados corporativos relevantes.\n\nUn sentimiento neutral en foros de operadores minoristas puede leerse de dos formas:\n\n1. **Cautela activa**: los participantes tienen posiciones abiertas pero no están convencidos de la dirección del mercado.\n2. **Falta de catalizador**: no hay un evento próximo lo suficientemente claro como para generar convicción en ninguna dirección.\n\nAmbas lecturas apuntan a lo mismo: el mercado está en modo de observación.\n\n## Compartir posiciones sin análisis: un patrón recurrente\n\nOtro hilo que tuvo actividad fue el de intercambio de posiciones entre usuarios. Este tipo de conversación es común en mercados laterales o de baja volatilidad. Cuando no hay noticias que dominen, los operadores minoristas tienden a comparar apuestas entre sí más que a reaccionar a eventos externos.\n\nEsto no es un indicador de dirección del mercado, pero sí es un indicio de que la semana empezó sin un tema dominante que jalara la atención hacia un sector o activo específico.\n\n## Lo que no apareció en la conversación\n\nTan importante como lo que se discutió es lo que no se mencionó. Durante esta jornada no circularon con fuerza noticias sobre:\n\n- Movimientos significativos en tasas de interés o comunicados de bancos centrales\n- Resultados corporativos que generaran reacción\n- Datos de empleo o inflación recientes\n- Tensiones geopolíticas con impacto directo en materias primas o divisas\n\nEsa ausencia de ruido es, paradójicamente, información. Los mercados no operan solo con lo que pasa, también con lo que se espera que pase.\n\n## Preguntas frecuentes\n\n**¿Por qué importa el sentimiento en foros como Reddit para entender el mercado?**\nLos foros de operadores minoristas concentran a millones de participantes con posiciones reales. Su sentimiento agregado, aunque ruidoso, puede reflejar tendencias de posicionamiento que eventualmente se manifiestan en volúmenes y precios. No reemplaza el análisis fundamental, pero es un dato más de contexto.\n\n**¿Un sentimiento neutral significa que no hay nada que observar?**\nNo. Un sentimiento neutral en un momento de alta incertidumbre puede preceder movimientos bruscos cuando finalmente llega un catalizador. La ausencia de convicción no equivale a estabilidad garantizada.\n\n**¿Por qué el precio del petróleo afecta a mercados que no tienen nada que ver con energía?**\nEl petróleo incide en los costos de producción y transporte de casi todos los sectores. Cuando sube, presiona los márgenes corporativos y puede alimentar inflación, lo que a su vez afecta las decisiones de los bancos centrales sobre tasas de interés. Por eso su movimiento se sigue de cerca incluso en carteras sin exposición directa a energía.\n\n## En resumen\n\nLa primera semana de julio 2026 arrancó con el mercado en pausa. El precio del petróleo generó preguntas sin respuesta clara. El sentimiento en foros minoristas se mantuvo neutral. No hubo catalizadores dominantes ni datos económicos que movieran la conversación en una dirección definida.\n\nEn semanas así, el trabajo del mercado es acumular información antes del siguiente movimiento. Las noticias que lleguen en los próximos días determinarán si esa pausa se convierte en tendencia o en ruido pasajero.\n\n---\n\n*Mal Mercado es contenido educativo e informativo de análisis general de mercados: la misma información para todos los lectores. No es asesoría de inversión personalizada ni recomendación individualizada; no somos asesores registrados ante la CNBV. Invertir implica riesgo de pérdida. Los rendimientos pasados no garantizan rendimientos futuros. Cada quien es responsable de sus propias decisiones.*", "images": ["public/media/blog/2026-07-06-mercado-hero.png", "public/media/blog/2026-07-06-mercado-foto1.jpg", "public/media/blog/2026-07-06-mercado-foto2.jpg"], "image_credits": ["Ecelan · BY-SA · vía wikimedia"], "sources": ["https://www.reddit.com/r/wallstreetbets/comments/1uosy1d/daily_discussion_thread_for_july_6_2026/", "https://www.reddit.com/r/wallstreetbets/comments/1uootpg/one_of_you_is_looking_for_divine_intervention/", "https://www.reddit.com/r/wallstreetbets/comments/1uok1x3/what_is_going_on_with_oil_prices/", "https://www.reddit.com/r/wallstreetbets/comments/1uoxoy3/wishing_extra_nuggies/", "https://www.reddit.com/r/wallstreetbets/comments/1uobx5h/what_are_your_moves_tomorrow_july_6_2026/", "https://www.reddit.com/r/wallstreetbets/comments/1uoab53/position_sharing_circle/"], "read_min": 4, "category": "Macro", "tags": ["mercados julio 2026", "precio del petroleo", "sentimiento del mercado", "operadores minoristas", "wall street", "analisis semanal"], "social": {"youtube": "título: Mercados en pausa: qué observa Wall Street en la primera semana de julio 2026 | descripción: Cuando el ruido baja, el posicionamiento habla más que los titulares. Esta semana arrancó sin grandes catalizadores: petróleo con preguntas abiertas, sentimiento neutral en foros de operadores y una conversación dominada por el intercambio de posiciones sin dirección clara. Mal Mercado analiza qué significa todo eso y por qué la ausencia de noticias también es información. Análisis completo en el blog.", "instagram": "La primera semana de julio 2026 arrancó sin catalizadores claros. El petróleo concentró las preguntas, el sentimiento se midió en cero y los foros de Wall Street mostraron algo que pasa más seguido de lo que parece: el mercado en modo observación. Cuando no hay ruido, el posicionamiento es el dato. Análisis completo en el blog de Mal Mercado, link en bio. #MalMercado #MercadosFinancieros #Petróleo #WallStreet #Análisis #TradingLatam #Finanzas", "facebook": "La primera semana completa de julio 2026 llegó sin grandes noticias. Nada de datos de empleo, sin comunicados de bancos centrales, sin resultados corporativos que movieran el tablero. Y sin embargo, los foros más activos de Wall Street no estuvieron en silencio: la conversación giró en torno al petróleo y al intercambio de posiciones entre operadores que tampoco tenían una convicción clara de dirección.\n\nEso, paradójicamente, es información. Un sentimiento neutral en momentos de poca claridad puede anteceder movimientos bruscos cuando finalmente aparece un catalizador. El mercado no opera solo con lo que pasa, también con lo que se espera que pase.\n\nMal Mercado analizó qué observaron los operadores minoristas el 6 de julio, qué factores mantienen en vilo al precio del crudo y por qué la ausencia de ruido es un dato que vale la pena leer. El análisis completo está disponible en el blog.", "tiktok": "La semana arrancó sin noticias. El mercado en pausa total. Pero eso también dice algo. Cuando el sentimiento se mide en cero y el único tema que circula es el petróleo sin respuesta clara, el posicionamiento se vuelve más relevante que cualquier titular. Mal Mercado lo analiza. #MalMercado #Petróleo #MercadosFinancieros #Trading", "x": "La primera semana de julio 2026 arrancó sin catalizadores. Sentimiento neutral, conversación centrada en petróleo y operadores comparando posiciones sin convicción. Cuando baja el ruido, el posicionamiento es el dato. Análisis en el blog de Mal Mercado.", "threads": "Mercados en pausa. Sentimiento en cero, petróleo con preguntas sin respuesta y operadores en modo observación. La ausencia de ruido también es información. Mal Mercado analiza qué observó Wall Street la primera semana de julio 2026.", "linkedin": "La primera semana de julio 2026 es un caso interesante para quienes siguen la dinámica de los mercados: arrancó sin un solo catalizador relevante. Sin datos macroeconómicos, sin comunicados de política monetaria, sin resultados corporativos. Y aun así, los foros de operadores minoristas más activos de Wall Street registraron actividad con un tema recurrente: el precio del petróleo y la incertidumbre sobre los factores que lo determinan.\n\nEn Mal Mercado rastreamos ese tipo de señales porque el sentimiento agregado de millones de participantes con posiciones reales es un dato de contexto que complementa el análisis fundamental. Un sentimiento medido en cero, como el observado el 6 de julio, no significa inactividad: puede reflejar cautela activa o simplemente la ausencia de un evento con suficiente peso para generar convicción en alguna dirección. Ambas lecturas apuntan a lo mismo: el mercado está esperando.\n\nEl análisis completo de esta jornada, incluyendo los factores que mantienen abierta la pregunta sobre el crudo y lo que no apareció en la conversación, está disponible en el blog de Mal Mercado."}}}